data_mem.v
module data_mem(
    input   wire    [31:0]  w_data,
    input   wire            w_en,
    input   wire    [31:0]  addr,
    input   wire            clk,
    output  wire    [31:0]  r_data
);
    
    reg [31:0]  mem[1023:0];

    assign r_data = mem[addr >> 2];
    always @(posedge clk) begin
        if(w_en == 1'b1) begin
            mem[addr >> 2] <= w_data;
        end
    end

endmodule

pipeline_interlock.v
module pipeline_interlock(
    input   wire    [6:0]   opcode,
    input   wire    [4:0]   rd_addr,
    input   wire    [4:0]   rs1_addr,
    input   wire    [4:0]   rs2_addr,
    input   wire            clk,
    output  reg             stall = 0
);

    reg         load_flag = 0; 
    reg [4:0]   p_rd_addr;

    always @(posedge clk) begin
        if(opcode == 7'b0000011) begin
            p_rd_addr <= rd_addr;
            load_flag <= 1;
            stall <= 0;
        end else if(load_flag) begin
            if((p_rd_addr == rs1_addr) || (p_rd_addr == rs2_addr)) begin
                stall <= 1;
            end else begin
                stall <= 0;
            end
            load_flag <= 0;
        end else begin
            stall <= 0;
        end
    end
endmodule

regfile.v
module regfile(
    input   wire [4:0]   rd_addr,
    input   wire [4:0]   rs1_addr,
    input   wire [4:0]   rs2_addr,
    input   wire [31:0]  w_data,
    input   wire         w_en,
    output  wire [31:0]  rs1_data,
    output  wire [31:0]  rs2_data,
    input   wire         clk
);

    reg [31:0] register[0:31];

    assign rs1_data = ((rs1_addr == rd_addr) && (rs1_addr != 5'b00000)) ? w_data 
                                                                        : register[rs1_addr];
    assign rs2_data = ((rs2_addr == rd_addr) && (rs2_addr != 5'b00000)) ? w_data 
                                                                        : register[rs2_addr];

    assign rs1_data = (rs1_addr == rd_addr) ? w_data : registers[rs1_addr];

    initial begin
        register[0] = 32'h0000_0000;
    end

    always @(posedge clk) begin
        if(w_en == 1 && rd_addr != 5'b00000) begin
            register[rd_addr] <= w_data;
        end else begin
            register[rd_addr] <= register[rd_addr];
        end
    end
endmodule

ALU.v
module ALU(
    input   wire    [3:0]   alu_ctrl,
    input   wire    [31:0]  alu_data_1,
    input   wire    [31:0]  alu_data_2,
    output  wire    [31:0]  alu_out
);

parameter ALU_ADD   = 4'h0;
parameter ALU_SUB   = 4'h1;
parameter ALU_XOR   = 4'h2;
parameter ALU_OR    = 4'h3;
parameter ALU_AND   = 4'h4;
parameter ALU_SLL   = 4'h5;
parameter ALU_SRL   = 4'h6;
parameter ALU_SRA   = 4'h7;
parameter ALU_SLT   = 4'h8;
parameter ALU_SLTU  = 4'h9;


    assign alu_out = alu_exec(alu_ctrl, alu_data_1, alu_data_2);

    function [31:0] alu_exec(
        input   [3:0]   alu_ctrl,
        input   [31:0]  alu_data_1,
        input   [31:0]  alu_data_2 
    );
        begin
            case(alu_ctrl)
                ALU_ADD:    alu_exec = alu_data_1 + alu_data_2;
                ALU_SUB:    alu_exec = alu_data_1 - alu_data_2;
                ALU_XOR:    alu_exec = alu_data_1 ^ alu_data_2;
                ALU_OR:     alu_exec = alu_data_1 | alu_data_2;
                ALU_AND:    alu_exec = alu_data_1 & alu_data_2;
                ALU_SLL:    alu_exec = alu_data_1 << alu_data_2;
                ALU_SRL:    alu_exec = alu_data_1 >> alu_data_2;
                ALU_SRA:    alu_exec = $signed(alu_data_1) >>> $signed(alu_data_2);
                ALU_SLT:    alu_exec = alu_data_1 < alu_data_2;
                ALU_SLTU:   alu_exec = $signed(alu_data_1) < $signed(alu_data_2);
            endcase
        end
    endfunction
endmodule

ALU_decoder.v
module ALU_decoder(
    input   wire    [6:0]   opcode,
    input   wire    [2:0]   funct3,
    input   wire    [6:0]   funct7,
    output  wire    [3:0]   alu_ctrl 
);

parameter ALU_ADD   = 4'h0;
parameter ALU_SUB   = 4'h1;
parameter ALU_XOR   = 4'h2;
parameter ALU_OR    = 4'h3;
parameter ALU_AND   = 4'h4;
parameter ALU_SLL   = 4'h5;
parameter ALU_SRL   = 4'h6;
parameter ALU_SRA   = 4'h7;
parameter ALU_SLT   = 4'h8;
parameter ALU_SLTU  = 4'h9;

    assign alu_ctrl = alu_dec(opcode, funct3, funct7);

    function [3:0] alu_dec(
        input   [6:0]   opcode,
        input   [2:0]   funct3,
        input   [6:0]   funct7
    );
        begin
            case(opcode)
                7'b0110011: begin
                    case(funct3)
                        3'h0: begin
                            case(funct7)
                                7'h00: alu_dec = ALU_ADD;
                                7'h20: alu_dec = ALU_SUB;
                            endcase
                        end
                        3'h4: alu_dec = ALU_XOR;
                        3'h6: alu_dec = ALU_OR;
                        3'h7: alu_dec = ALU_AND;
                        3'h1: alu_dec = ALU_SLL;
                        3'h5: begin
                            case(funct7)
                                7'h00: alu_dec = ALU_SRL;
                                7'h20: alu_dec = ALU_SRA;
                            endcase
                        end
                        3'h2: alu_dec = ALU_SLT;
                        3'h3: alu_dec = ALU_SLTU;
                    endcase
                end
                7'b0010011: begin
                    case(funct3)
                        3'h0: alu_dec = ALU_ADD;
                        3'h4: alu_dec = ALU_XOR;
                        3'h6: alu_dec = ALU_OR;
                        3'h7: alu_dec = ALU_AND;
                        3'h1: alu_dec = ALU_SLL;
                        3'h5: begin
                            case(funct7)
                                7'h00: alu_dec = ALU_SRL;
                                7'h20: alu_dec = ALU_SRA;
                            endcase
                        end
                        3'h2: alu_dec = ALU_SLT;
                        3'h3: alu_dec = ALU_SLTU;
                    endcase
                end
                7'b0000011: alu_dec = ALU_ADD;
                7'b0100011: alu_dec = ALU_ADD;
            endcase
        end
    endfunction
endmodule

main_controller.v
module main_controller(
    input   wire    [6:0]   opcode,
    output  wire            rs2_imm_sel,    // 0: rs2, 1:imm
    output  wire            reg_w_en,       // 0: disable, 1:enable
    output  wire            mem_w_en,       // 0: disable, 1:enable
    output  wire            mem_alu_sel,    // 0: memd, 1: alud
    output  wire            imm_SI_sel      // 0: S_imm, 1:I_imm
);

    assign {rs2_imm_sel, reg_w_en, mem_w_en, mem_alu_sel, imm_SI_sel} = decoder(opcode);

    function [4:0] decoder(
        input [6:0] opcode
    );
        begin
            case(opcode)
                7'b0110011: decoder = 5'b01010;  //Rtype
                7'b0010011: decoder = 5'b11011;  //Itype
                7'b0100011: decoder = 5'b10100;  //Store
                7'b0000011: decoder = 5'b11001;  //Load
                default:    decoder = 5'b00000;
            endcase
        end
    endfunction

endmodule

main_decoder.v
module main_decoder(
    input   wire    [31:0]  instr,
    output  wire    [6:0]   opcode,
    output  wire    [2:0]   funct3,
    output  wire    [6:0]   funct7,
    output  wire    [4:0]   rd_addr,
    output  wire    [4:0]   rs1_addr,
    output  wire    [4:0]   rs2_addr,
    output  wire    [31:0]  imm_I,
    output  wire    [31:0]  imm_S,
    output  wire    [31:0]  imm_B,
    output  wire    [31:0]  uimm_B,
    output  wire    [31:0]  imm_U,
    output  wire    [31:0]  imm_J,
    output  wire    [31:0]  uimm_J
);

    assign opcode   = instr[6:0];
    assign funct3   = instr[14:12];
    assign funct7   = instr[31:25];
    assign rd_addr  = instr[11:7];
    assign rs1_addr = instr[19:15];
    assign rs2_addr = instr[24:20];
    assign imm_I    = instr[31] ? {20'hfffff, instr[31:20]} 
                                : {20'h00000, instr[31:20]};
    assign imm_S   = {20'h00000, instr[31:25], instr[11:7]};
    assign imm_B    = instr[31] ? {16'hffff, 3'b111, instr[31], instr[7], instr[30:25], instr[11:8], 1'b0}
                                : {16'h0000, 3'b000, instr[31], instr[7], instr[30:25], instr[11:8], 1'b0};
    assign uimm_B   = {16'h0000, 3'b000, instr[31], instr[7], instr[30:25], instr[11:8], 1'b0};
    assign imm_U    = {instr[31:12], 12'h000};
    assign imm_J    = instr[31] ? {8'hff, 3'b111, instr[31], instr[19:12], instr[20], instr[30:21], 1'b0}
                                : {8'h00, 3'b000, instr[31], instr[19:12], instr[20], instr[30:21], 1'b0};
    assign uimm_J   = {8'h00, 3'b000, instr[31], instr[19:12], instr[20], instr[30:21], 1'b0};
endmodule

cpu.v
module cpu(
    input   wire            clk,
    input   wire    [31:0]  instr,
    output  reg     [31:0]  pc  = 32'h0000_0000,
    output  reg             EX_MEM_mem_w_en = 0,
    output  reg     [31:0]  EX_MEM_alu_out  = 32'h0000_0000,
    output  wire    [31:0]  mem_w_data,
    input   wire    [31:0]  mem_r_data
);

    reg [31:0]  IF_ID_instr = 32'h0000_0000;

    reg [31:0]  ID_EX_rs1_data  = 32'h0000_0000;
    reg [31:0]  ID_EX_rs2_data  = 32'h0000_0000;
    reg [4:0]   ID_EX_rs1_addr  = 5'b00000;
    reg [4:0]   ID_EX_rs2_addr  = 5'b00000;
    reg [4:0]   ID_EX_rd_addr   = 5'b00000;
    reg [31:0]  ID_EX_imm_I     = 32'h0000_0000;
    reg [31:0]  ID_EX_imm_S     = 32'h0000_0000;
    reg [3:0]   ID_EX_alu_ctrl  = 4'h0;
    reg [6:0]   ID_EX_opcode    = 7'b0000000;
    reg         ID_EX_rs2_imm_sel   = 0;
    reg         ID_EX_reg_w_en      = 0;
    reg         ID_EX_mem_w_en      = 0;
    reg         ID_EX_mem_alu_sel   = 0;
    reg         ID_EX_imm_SI_sel    = 0;

    reg         EX_MEM_reg_w_en = 0;
    reg [4:0]   EX_MEM_rd_addr  = 5'b00000;
    reg [4:0]   EX_MEM_rs2_addr = 5'b00000;
    reg         EX_MEM_mem_alu_sel = 0;
    reg [31:0]  EX_MEM_rs2_data = 32'h0000_0000;

    reg [31:0]  MEM_WB_mem_r_data   = 32'h0000_0000;
    reg [31:0]  MEM_WB_alu_out      = 32'h0000_0000;
    reg [4:0]   MEM_WB_rd_addr      = 5'b00000;
    reg         MEM_WB_reg_w_en     = 0;
    reg         MEM_WB_mem_alu_sel  = 0;

    wire    [6:0]   opcode;
    wire    [2:0]   funct3;
    wire    [6:0]   funct7;
    wire    [4:0]   rd_addr;
    wire    [4:0]   rs1_addr;
    wire    [4:0]   rs2_addr;
    wire    [31:0]  imm_I;
    wire    [31:0]  imm_S;
    wire    [31:0]  imm_data;

    wire            rs2_imm_sel;
    wire            reg_w_en;
    wire            mem_w_en;
    wire            mem_alu_sel;

    wire    [3:0]   alu_ctrl;

    wire    [31:0]  alu_data_1;
    wire    [31:0]  alu_data_2;
    wire    [31:0]  alu_out;

    wire    [31:0]  rs1_data;
    wire    [31:0]  rs2_data;
    wire    [31:0]  reg_w_data;

    wire            stall;

    main_decoder    main_decoder(
                        .instr      (instr      ),
                        .opcode     (opcode     ),
                        .funct3     (funct3     ),
                        .funct7     (funct7     ),
                        .rd_addr    (rd_addr    ),
                        .rs1_addr   (rs1_addr   ),
                        .rs2_addr   (rs2_addr   ),
                        .imm_I      (imm_I      ),
                        .imm_S      (imm_S      )
                    );

    main_controller main_controller(
                        .opcode         (opcode         ),
                        .rs2_imm_sel    (rs2_imm_sel    ),
                        .reg_w_en       (reg_w_en       ),
                        .mem_w_en       (mem_w_en       ),
                        .mem_alu_sel    (mem_alu_sel    ),
                        .imm_SI_sel     (imm_SI_sel     )
                    );

    ALU_decoder     ALU_decoder(
                        .opcode     (opcode     ),
                        .funct3     (funct3     ),
                        .funct7     (funct7     ),
                        .alu_ctrl   (alu_ctrl   )
                    );

    assign imm_data = ID_EX_imm_SI_sel ? ID_EX_imm_I : ID_EX_imm_S;
    assign alu_data_1 = (ID_EX_rs1_addr == EX_MEM_rd_addr) & EX_MEM_reg_w_en    ? EX_MEM_alu_out
                      : (ID_EX_rs1_addr == MEM_WB_rd_addr) & MEM_WB_reg_w_en    ? reg_w_data     //MEM_WB_alu_out
                                                                                : ID_EX_rs1_data;
    assign alu_data_2 = ID_EX_rs2_imm_sel                  ? imm_data 
                      : (ID_EX_rs2_addr == EX_MEM_rd_addr) & EX_MEM_reg_w_en    ? EX_MEM_alu_out
                      : (ID_EX_rs2_addr == MEM_WB_rd_addr) & MEM_WB_reg_w_en    ? reg_w_data     //MEM_WB_alu_out
                      : ID_EX_rs2_data; 
    ALU             ALU(
                        .alu_ctrl   (ID_EX_alu_ctrl ),
                        .alu_data_1 (alu_data_1     ),
                        .alu_data_2 (alu_data_2     ),
                        .alu_out    (alu_out        )
                    );

    assign reg_w_data = MEM_WB_mem_alu_sel ? MEM_WB_alu_out : MEM_WB_mem_r_data;
    regfile         regfile(
                        .rs1_addr   (rs1_addr           ),
                        .rs2_addr   (rs2_addr           ),
                        .rs1_data   (rs1_data           ),
                        .rs2_data   (rs2_data           ),
                        .rd_addr    (MEM_WB_rd_addr     ),
                        .w_data     (reg_w_data         ),
                        .w_en       (MEM_WB_reg_w_en    ),
                        .clk        (clk)
                    );

    assign mem_w_data = (MEM_WB_rd_addr == EX_MEM_rs2_addr) ? reg_w_data
                                                            : MEM_WB_mem_r_data;

    pipeline_interlock  pipeline_interlock(
                            .opcode     (opcode   ),
                            .rd_addr    (rd_addr  ),
                            .rs1_addr   (rs1_addr ),
                            .rs2_addr   (rs2_addr ),
                            .clk        (clk            ),
                            .stall      (stall          )
                        );

    always @(posedge clk) begin
        if(stall) begin
            pc = pc;
        end else begin
            pc = pc + 32'h4;
        end
    end

    always @(posedge clk) begin
        if(stall) begin
            IF_ID_instr <= IF_ID_instr;
        end else begin
            IF_ID_instr <= instr;
        end
    end

    always @(posedge clk) begin
        if(stall) begin
            ID_EX_rs1_data      <= ID_EX_rs1_data;
            ID_EX_rs2_data      <= ID_EX_rs2_data;
            ID_EX_rs1_addr      <= ID_EX_rs1_addr;
            ID_EX_rs2_addr      <= ID_EX_rs2_addr;
            ID_EX_rd_addr       <= ID_EX_rd_addr;
            ID_EX_imm_I         <= ID_EX_imm_I;
            ID_EX_imm_S         <= ID_EX_imm_S;
            ID_EX_alu_ctrl      <= ID_EX_alu_ctrl;
            ID_EX_rs2_imm_sel   <= ID_EX_rs2_imm_sel;
            ID_EX_reg_w_en      <= ID_EX_reg_w_en;
            ID_EX_mem_w_en      <= ID_EX_mem_w_en;
            ID_EX_mem_alu_sel   <= ID_EX_mem_alu_sel;
            ID_EX_imm_SI_sel    <= ID_EX_imm_SI_sel;
            ID_EX_opcode        <= ID_EX_opcode;
        end else begin
            ID_EX_rs1_data      <= rs1_data;
            ID_EX_rs2_data      <= rs2_data;
            ID_EX_rs1_addr      <= rs1_addr;
            ID_EX_rs2_addr      <= rs2_addr;
            ID_EX_rd_addr       <= rd_addr;
            ID_EX_imm_I         <= imm_I;
            ID_EX_imm_S         <= imm_S;
            ID_EX_alu_ctrl      <= alu_ctrl;
            ID_EX_rs2_imm_sel   <= rs2_imm_sel;
            ID_EX_reg_w_en      <= reg_w_en;
            ID_EX_mem_w_en      <= mem_w_en;
            ID_EX_mem_alu_sel   <= mem_alu_sel;
            ID_EX_imm_SI_sel    <= imm_SI_sel;
            ID_EX_opcode        <= opcode;
        end
    end

    always @(posedge clk) begin
        EX_MEM_alu_out      <= alu_out;
        EX_MEM_rd_addr      <= ID_EX_rd_addr;
        EX_MEM_rs2_addr     <= ID_EX_rs2_addr;
        EX_MEM_mem_w_en     <= ID_EX_mem_w_en;
        EX_MEM_reg_w_en     <= ID_EX_reg_w_en;
        EX_MEM_rs2_data     <= ID_EX_rs2_data;
        EX_MEM_mem_alu_sel  <= ID_EX_mem_alu_sel;
    end

    always @(posedge clk) begin
        MEM_WB_mem_r_data   <= mem_r_data;
        MEM_WB_alu_out      <= EX_MEM_alu_out;
        MEM_WB_rd_addr      <= EX_MEM_rd_addr;
        MEM_WB_reg_w_en     <= EX_MEM_reg_w_en; 
        MEM_WB_mem_alu_sel  <= EX_MEM_mem_alu_sel;
    end
endmodule

instr_mem.v
module instr_mem(
    input   [31:0] addr,
    output  [31:0] instr
);

    reg [31:0] mem[1023:0];

    assign instr = mem[addr >> 2];

    initial begin
        mem[0] = 32'h01400313;
        mem[1] = 32'h00602023;
        mem[2] = 32'h00000013;
        mem[3] = 32'h00000013;
        mem[4] = 32'h00000013;
        mem[5] = 32'h00002e03;
        mem[6] = 32'h000e0eb3;
        mem[7] = 32'h00000013;
        mem[8] = 32'h00000013;
        mem[9] = 32'h00000013;
        mem[10] = 32'h00000013;
        mem[11] = 32'h00000013;
        mem[12] = 32'h00000013;
    end
endmodule

computer.v
module computer(
    input   wire    clk
);

    wire    [31:0]  pc;
    wire    [31:0]  instr;
    wire            mem_w_en;
    wire    [31:0]  alu_out;
    wire    [31:0]  mem_r_data;
    wire    [31:0]  mem_w_data;

    instr_mem   instr_mem(
                    .addr   (pc     ),
                    .instr  (instr  )
                );

    cpu         cpu(
                    .clk                (clk        ),
                    .pc                 (pc         ),
                    .instr              (instr      ),
                    .EX_MEM_mem_w_en    (mem_w_en   ),
                    .EX_MEM_alu_out     (alu_out    ),
                    .mem_w_data         (mem_w_data ),
                    .mem_r_data         (mem_r_data ) 
                );
    
    data_mem    data_mem(
                    .w_data (mem_w_data ), 
                    .w_en   (mem_w_en   ), 
                    .addr   (alu_out    ),
                    .r_data (mem_r_data ),
                    .clk    (clk        )
                );
endmodule

test_bench.v
module test_bench();
    reg clk = 0;

    computer computer(
                .clk(clk)
             );

    always #1 begin
        clk = ~clk;
    end

    initial begin
        $dumpfile("wave.vcd");
        $dumpvars(0, computer);
        #1000;
        $finish;
    end
endmodule

wave.vcd
$date
	Mon Apr 20 03:20:59 2020
$end
$version
	Icarus Verilog
$end
$timescale
	1s
$end
$scope module test_bench $end
$scope module computer $end
$var wire 1 ! clk $end
$var wire 32 " pc [31:0] $end
$var wire 1 # mem_w_en $end
$var wire 32 $ mem_w_data [31:0] $end
$var wire 32 % mem_r_data [31:0] $end
$var wire 32 & instr [31:0] $end
$var wire 32 ' alu_out [31:0] $end
$scope module cpu $end
$var wire 1 ! clk $end
$var wire 1 ( stall $end
$var wire 1 ) rs2_imm_sel $end
$var wire 32 * rs2_data [31:0] $end
$var wire 5 + rs2_addr [4:0] $end
$var wire 32 , rs1_data [31:0] $end
$var wire 5 - rs1_addr [4:0] $end
$var wire 1 . reg_w_en $end
$var wire 32 / reg_w_data [31:0] $end
$var wire 5 0 rd_addr [4:0] $end
$var wire 7 1 opcode [6:0] $end
$var wire 1 2 mem_w_en $end
$var wire 32 3 mem_w_data [31:0] $end
$var wire 32 4 mem_r_data [31:0] $end
$var wire 1 5 mem_alu_sel $end
$var wire 32 6 instr [31:0] $end
$var wire 32 7 imm_data [31:0] $end
$var wire 1 8 imm_SI_sel $end
$var wire 32 9 imm_S [31:0] $end
$var wire 32 : imm_I [31:0] $end
$var wire 7 ; funct7 [6:0] $end
$var wire 3 < funct3 [2:0] $end
$var wire 32 = alu_out [31:0] $end
$var wire 32 > alu_data_2 [31:0] $end
$var wire 32 ? alu_data_1 [31:0] $end
$var wire 4 @ alu_ctrl [3:0] $end
$var reg 32 A EX_MEM_alu_out [31:0] $end
$var reg 1 B EX_MEM_mem_alu_sel $end
$var reg 1 # EX_MEM_mem_w_en $end
$var reg 5 C EX_MEM_rd_addr [4:0] $end
$var reg 1 D EX_MEM_reg_w_en $end
$var reg 5 E EX_MEM_rs2_addr [4:0] $end
$var reg 32 F EX_MEM_rs2_data [31:0] $end
$var reg 4 G ID_EX_alu_ctrl [3:0] $end
$var reg 32 H ID_EX_imm_I [31:0] $end
$var reg 32 I ID_EX_imm_S [31:0] $end
$var reg 1 J ID_EX_imm_SI_sel $end
$var reg 1 K ID_EX_mem_alu_sel $end
$var reg 1 L ID_EX_mem_w_en $end
$var reg 7 M ID_EX_opcode [6:0] $end
$var reg 5 N ID_EX_rd_addr [4:0] $end
$var reg 1 O ID_EX_reg_w_en $end
$var reg 5 P ID_EX_rs1_addr [4:0] $end
$var reg 32 Q ID_EX_rs1_data [31:0] $end
$var reg 5 R ID_EX_rs2_addr [4:0] $end
$var reg 32 S ID_EX_rs2_data [31:0] $end
$var reg 1 T ID_EX_rs2_imm_sel $end
$var reg 32 U IF_ID_instr [31:0] $end
$var reg 32 V MEM_WB_alu_out [31:0] $end
$var reg 1 W MEM_WB_mem_alu_sel $end
$var reg 32 X MEM_WB_mem_r_data [31:0] $end
$var reg 5 Y MEM_WB_rd_addr [4:0] $end
$var reg 1 Z MEM_WB_reg_w_en $end
$var reg 32 [ pc [31:0] $end
$scope module ALU $end
$var wire 4 \ alu_ctrl [3:0] $end
$var wire 32 ] alu_data_1 [31:0] $end
$var wire 32 ^ alu_data_2 [31:0] $end
$var wire 32 _ alu_out [31:0] $end
$scope function alu_exec $end
$var reg 4 ` alu_ctrl [3:0] $end
$var reg 32 a alu_data_1 [31:0] $end
$var reg 32 b alu_data_2 [31:0] $end
$var reg 32 c alu_exec [31:0] $end
$upscope $end
$upscope $end
$scope module ALU_decoder $end
$var wire 7 d opcode [6:0] $end
$var wire 7 e funct7 [6:0] $end
$var wire 3 f funct3 [2:0] $end
$var wire 4 g alu_ctrl [3:0] $end
$scope function alu_dec $end
$var reg 4 h alu_dec [3:0] $end
$var reg 3 i funct3 [2:0] $end
$var reg 7 j funct7 [6:0] $end
$var reg 7 k opcode [6:0] $end
$upscope $end
$upscope $end
$scope module main_controller $end
$var wire 1 ) rs2_imm_sel $end
$var wire 1 . reg_w_en $end
$var wire 7 l opcode [6:0] $end
$var wire 1 2 mem_w_en $end
$var wire 1 5 mem_alu_sel $end
$var wire 1 8 imm_SI_sel $end
$scope function decoder $end
$var reg 5 m decoder [4:0] $end
$var reg 7 n opcode [6:0] $end
$upscope $end
$upscope $end
$scope module main_decoder $end
$var wire 32 o uimm_J [31:0] $end
$var wire 32 p uimm_B [31:0] $end
$var wire 5 q rs2_addr [4:0] $end
$var wire 5 r rs1_addr [4:0] $end
$var wire 5 s rd_addr [4:0] $end
$var wire 7 t opcode [6:0] $end
$var wire 32 u instr [31:0] $end
$var wire 32 v imm_U [31:0] $end
$var wire 32 w imm_S [31:0] $end
$var wire 32 x imm_J [31:0] $end
$var wire 32 y imm_I [31:0] $end
$var wire 32 z imm_B [31:0] $end
$var wire 7 { funct7 [6:0] $end
$var wire 3 | funct3 [2:0] $end
$upscope $end
$scope module pipeline_interlock $end
$var wire 1 ! clk $end
$var wire 7 } opcode [6:0] $end
$var wire 5 ~ rd_addr [4:0] $end
$var wire 5 !" rs1_addr [4:0] $end
$var wire 5 "" rs2_addr [4:0] $end
$var reg 1 #" load_flag $end
$var reg 5 $" p_rd_addr [4:0] $end
$var reg 1 ( stall $end
$upscope $end
$scope module regfile $end
$var wire 1 ! clk $end
$var wire 5 %" rd_addr [4:0] $end
$var wire 5 &" rs1_addr [4:0] $end
$var wire 5 '" rs2_addr [4:0] $end
$var wire 32 (" w_data [31:0] $end
$var wire 1 Z w_en $end
$var wire 32 )" rs2_data [31:0] $end
$var wire 32 *" rs1_data [31:0] $end
$upscope $end
$upscope $end
$scope module data_mem $end
$var wire 32 +" addr [31:0] $end
$var wire 1 ! clk $end
$var wire 32 ," r_data [31:0] $end
$var wire 32 -" w_data [31:0] $end
$var wire 1 # w_en $end
$upscope $end
$scope module instr_mem $end
$var wire 32 ." addr [31:0] $end
$var wire 32 /" instr [31:0] $end
$upscope $end
$upscope $end
$upscope $end
$enddefinitions $end
#0
$dumpvars
b1010000000000001100010011 /"
b0 ."
b0 -"
bx ,"
b0 +"
b0 *"
bx )"
b0 ("
b10100 '"
b0 &"
b0 %"
bx $"
0#"
b10100 ""
b0 !"
b110 ~
b10011 }
b0 |
b0 {
b110 z
b10100 y
b10100 x
b110 w
b1010000000000000000000000 v
b1010000000000001100010011 u
b10011 t
b110 s
b0 r
b10100 q
b110 p
b10100 o
b10011 n
b11011 m
b10011 l
b10011 k
b0 j
b0 i
b0 h
b0 g
b0 f
b0 e
b10011 d
b0 c
b0 b
b0 a
b0 `
b0 _
b0 ^
b0 ]
b0 \
b0 [
0Z
b0 Y
b0 X
0W
b0 V
b0 U
0T
b0 S
b0 R
b0 Q
b0 P
0O
b0 N
b0 M
0L
0K
0J
b0 I
b0 H
b0 G
b0 F
b0 E
0D
b0 C
0B
b0 A
b0 @
b0 ?
b0 >
b0 =
b0 <
b0 ;
b10100 :
b110 9
18
b0 7
b1010000000000001100010011 6
15
bx 4
b0 3
02
b10011 1
b110 0
b0 /
1.
b0 -
b0 ,
b10100 +
bx *
1)
0(
b0 '
b1010000000000001100010011 &
bx %
b0 $
0#
b0 "
0!
$end
#1
b10100 =
b10100 _
b10100 c
b10100 b
bx $
bx 3
bx -"
b10100 >
b10100 ^
b10100 7
bx /
bx ("
b1010000000000001100010011 U
b10011 M
1J
1K
1O
1T
b110 I
b10100 H
b110 N
b10100 R
bx S
bx X
08
05
12
0.
b10000000000110 x
b0 z
b110 :
b110 y
b10100 m
b100011 n
b10 i
b100011 k
b10000000000110 o
b11000000010000000000000 v
b0 p
b0 9
b0 w
b110 +
b110 q
b110 ""
b110 '"
b0 0
b0 s
b0 ~
b10 <
b10 f
b10 |
b100011 1
b100011 d
b100011 l
b100011 t
b100011 }
b11000000010000000100011 &
b11000000010000000100011 6
b11000000010000000100011 u
b11000000010000000100011 /"
b100 "
b100 [
b100 ."
1!
#2
0!
#3
b0 =
b0 _
b0 c
b0 b
b0 >
b0 ^
b0 7
1B
bx F
1D
b10100 E
b110 C
b10100 '
b10100 A
b10100 +"
b100011 M
0J
0K
1L
0O
b0 I
b110 H
b0 N
b110 R
b11000000010000000100011 U
18
15
02
1.
b0 x
b0 :
b0 y
b0 *
b0 )"
b11011 m
b10011 n
b0 i
b10011 k
b0 o
b0 v
b0 +
b0 q
b0 ""
b0 '"
b0 <
b0 f
b0 |
b10011 1
b10011 d
b10011 l
b10011 t
b10011 }
b10011 &
b10011 6
b10011 u
b10011 /"
b1000 "
b1000 [
b1000 ."
1!
#4
0!
#5
b10100 $
b10100 3
b10100 -"
b10100 /
b10100 ("
b10011 U
b10011 M
1J
1K
0L
1O
b0 H
b0 R
b0 S
0B
0D
1#
b110 E
b0 C
b0 '
b0 A
b0 +"
1W
1Z
b110 Y
b110 %"
b10100 V
b1100 "
b1100 [
b1100 ."
1!
#6
0!
#7
bx $
bx 3
bx -"
bx /
bx ("
b10100 %
b10100 4
b10100 ,"
0W
0Z
b0 Y
b0 %"
b0 V
1B
b0 F
1D
0#
b0 E
b10000 "
b10000 [
b10000 ."
1!
#8
0!
#9
b0 $
b0 3
b0 -"
b0 /
b0 ("
1W
1Z
b10100 X
05
b10000000000000 x
b11100 z
b11001 m
b11 n
b10 i
b11 k
b10000000000000 o
b10000000000000 v
b11100 p
b11100 9
b11100 w
b11100 0
b11100 s
b11100 ~
b10 <
b10 f
b10 |
b11 1
b11 d
b11 l
b11 t
b11 }
b10111000000011 &
b10111000000011 6
b10111000000011 u
b10111000000011 /"
b10100 "
b10100 [
b10100 ."
1!
#10
0!
#11
b11 M
0K
b11100 I
b11100 N
b10111000000011 U
1#"
b11100 $"
08
15
0)
b11100000000000000000 x
b100000011100 z
bx ,
bx *"
b1010 m
b110011 n
b0 i
b110011 k
b11100000000000000000 o
b11100000000000000000 v
b100000011100 p
b11101 9
b11101 w
b11100 -
b11100 r
b11100 !"
b11100 &"
b11101 0
b11101 s
b11101 ~
b0 <
b0 f
b0 |
b110011 1
b110011 d
b110011 l
b110011 t
b110011 }
b11100000111010110011 &
b11100000111010110011 6
b11100000111010110011 u
b11100000111010110011 /"
b11000 "
b11000 [
b11000 ."
1!
#12
0!
#13
b11101 7
0#"
1(
b11100000111010110011 U
b110011 M
0J
1K
0T
b11101 I
b11101 N
b11100 P
bx Q
0B
b11100 C
18
1)
b0 x
b0 z
b0 ,
b0 *"
b11011 m
b10011 n
b10011 k
b0 o
b0 v
b0 p
b0 9
b0 w
b0 -
b0 r
b0 !"
b0 &"
b0 0
b0 s
b0 ~
b10011 1
b10011 d
b10011 l
b10011 t
b10011 }
b10011 &
b10011 6
b10011 u
b10011 /"
b11100 "
b11100 [
b11100 ."
1!
#14
0!
#15
b10100 =
b10100 _
b10100 c
b10100 a
b10100 ?
b10100 ]
b10100 /
b10100 ("
b10100 $
b10100 3
b10100 -"
0W
b11100 Y
b11100 %"
1B
b11101 C
0(
1!
#16
0!
#17
b0 =
b0 _
b0 c
b0 a
b0 ?
b0 ]
b0 7
bx %
bx 4
bx ,"
b0 /
b0 ("
b10011 U
b10011 M
1J
1T
b0 I
b0 N
b0 P
b0 Q
b10100 '
b10100 A
b10100 +"
1W
b11101 Y
b11101 %"
b100000 "
b100000 [
b100000 ."
1!
#18
0!
#19
b10100 /
b10100 ("
bx $
bx 3
bx -"
b10100 %
b10100 4
b10100 ,"
b10100 V
bx X
b0 C
b0 '
b0 A
b0 +"
b100100 "
b100100 [
b100100 ."
1!
#20
0!
#21
b0 /
b0 ("
b0 $
b0 3
b0 -"
b0 Y
b0 %"
b0 V
b10100 X
b101000 "
b101000 [
b101000 ."
1!
#22
0!
#23
b101100 "
b101100 [
b101100 ."
1!
#24
0!
#25
b110000 "
b110000 [
b110000 ."
1!
#26
0!
#27
08
05
0.
0)
bx0 x
bx0 z
bx :
bx y
bx *
bx )"
bx ,
bx *"
b0 m
bx n
bx j
bx i
bx k
b0xxxxxxxxxxxxxxxxxxxx0 o
bx000000000000 v
b0xxxxxxxxxxxx0 p
b0xxxxxxxxxxxx 9
b0xxxxxxxxxxxx w
bx +
bx q
bx ""
bx '"
bx -
bx r
bx !"
bx &"
bx 0
bx s
bx ~
bx ;
bx e
bx {
bx <
bx f
bx |
bx 1
bx d
bx l
bx t
bx }
bx &
bx 6
bx u
bx /"
b110100 "
b110100 [
b110100 ."
1!
#28
0!
#29
bx b
bx >
bx ^
bx =
bx _
bx c
bx a
bx ?
bx ]
b0xxxxxxxxxxxx 7
bx U
bx M
0J
0K
0O
0T
b0xxxxxxxxxxxx I
bx H
bx N
bx R
bx P
bx S
bx Q
b111000 "
b111000 [
b111000 ."
1!
#30
0!
